EzEngine.cpython-313-x86_64-linux-gnu.so
src/__init__.py
src/convert_audio_to_text.py
EasyEngine-0.2.dist-info/LICENSE
EasyEngine-0.2.dist-info/METADATA
EasyEngine-0.2.dist-info/WHEEL
EasyEngine-0.2.dist-info/top_level.txt
EasyEngine-0.2.dist-info/RECORD
