Metadata-Version: 2.2
Name: EasyEngine
Version: 0.2
Summary: This a simple SDL2 based 2d UI engine. Used for creating windows without borders. Can render jpg, png, gif and simple grafics on screen like python-turtle. Can be used like C/CPP header or python lib. Suppport async work
Home-page: https://t.me/ArcaneDevStudio
Author: Namilsky
Author-email: alive6863@gmail.com
Project-URL: GitHub, https://GitHub.com/Nam4ik/EasyEngineLib
Keywords: Graphics 2d
Requires-Python: >=3.6
License-File: LICENSE
Dynamic: author
Dynamic: author-email
Dynamic: description
Dynamic: description-content-type
Dynamic: home-page
Dynamic: keywords
Dynamic: project-url
Dynamic: requires-python
Dynamic: summary
